README.md
setup.cfg
setup.py
pydkron/__init__.py
pydkron/client.py
pydkron/job.py
pydkron.egg-info/PKG-INFO
pydkron.egg-info/SOURCES.txt
pydkron.egg-info/dependency_links.txt
pydkron.egg-info/requires.txt
pydkron.egg-info/top_level.txt