Metadata-Version: 1.1
Name: pydkron
Version: 0.2.3
Summary: pydkron: Python Client for Dkron
Home-page: https://github.com/oldmantaiter/pydkron
Author: Tait Clarridge
Author-email: tait@clarridge.ca
License: MIT License
Download-URL: https://github.com/oldmantaiter/pydkron/archive/0.2.3.tar.gz
Keywords: dkron
Platform: UNKNOWN
Classifier: Development Status :: 5 - Production/Stable
Classifier: Intended Audience :: Developers
Classifier: Topic :: Software Development :: Build Tools
Classifier: License :: OSI Approved :: MIT License
Classifier: Programming Language :: Python :: 3
